{"837":{"prenom":"Bakary","nom":"COULIBALY","sexe":"M","statut":"REG","ecole":"","option_type":"CLASS","centre_examen":"REG FARABALA 2È C","cap":"FARABALA","academie":"ACADEMIE D'ENSEIGNEMENT DE KITA","examen":"DEF 2024","mention":""},"926":{"prenom":"Diby","nom":"COULIBALY","sexe":"F","statut":"REG","ecole":"","option_type":"CLASS","centre_examen":"REG FARABALA 2È C","cap":"FARABALA","academie":"ACADEMIE D'ENSEIGNEMENT DE KITA","examen":"DEF 2024","mention":""},"979":{"prenom":"Fanta","nom":"","sexe":"M","statut":"REG","ecole":"","option_type":"CLASS","centre_examen":"REG FARABALA 2È C","cap":"FARABALA","academie":"ACADEMIE D'ENSEIGNEMENT DE KITA","examen":"DEF 2024","mention":""},"1010":{"prenom":"Fatoumata Baba","nom":"COULIBALY","sexe":"F","statut":"REG","ecole":"","option_type":"CLASS","centre_examen":"REG FARABALA 2È C","cap":"FARABALA","academie":"ACADEMIE D'ENSEIGNEMENT DE KITA","examen":"DEF 2024","mention":""},"1852":{"prenom":"Boly","nom":"DEMBELE","sexe":"F","statut":"REG","ecole":"","option_type":"CLASS","centre_examen":"REG FARABALA 2È C","cap":"FARABALA","academie":"ACADEMIE D'ENSEIGNEMENT DE KITA","examen":"DEF 2024","mention":""},"1889":{"prenom":"Cheick Oumar","nom":"DEMBELE","sexe":"M","statut":"REG","ecole":"","option_type":"CLASS","centre_examen":"REG FARABALA 2È C","cap":"FARABALA","academie":"ACADEMIE D'ENSEIGNEMENT DE KITA","examen":"DEF 2024","mention":""},"2828":{"prenom":"Diakalaye","nom":"DIABATE","sexe":"M","statut":"REG","ecole":"","option_type":"CLASS","centre_examen":"REG FARABALA 2È C","cap":"FARABALA","academie":"ACADEMIE D'ENSEIGNEMENT DE KITA","examen":"DEF 2024","mention":""},"4382":{"prenom":"Djénéba","nom":"DIARRA","sexe":"F","statut":"REG","ecole":"","option_type":"CLASS","centre_examen":"REG FARABALA 2È C","cap":"FARABALA","academie":"ACADEMIE D'ENSEIGNEMENT DE KITA","examen":"DEF 2024","mention":""},"4803":{"prenom":"Sambou","nom":"DIAWARA","sexe":"F","statut":"REG","ecole":"","option_type":"CLASS","centre_examen":"REG FARABALA 2È C","cap":"FARABALA","academie":"ACADEMIE D'ENSEIGNEMENT DE KITA","examen":"DEF 2024","mention":""},"5931":{"prenom":"Rokia","nom":"KANOUTE","sexe":"F","statut":"REG","ecole":"","option_type":"CLASS","centre_examen":"REG FARABALA 2È C","cap":"FARABALA","academie":"ACADEMIE D'ENSEIGNEMENT DE KITA","examen":"DEF 2024","mention":""},"6194":{"prenom":"Aïssata","nom":"KEITA","sexe":"F","statut":"REG","ecole":"","option_type":"CLASS","centre_examen":"REG FARABALA 2È C","cap":"FARABALA","academie":"ACADEMIE D'ENSEIGNEMENT DE KITA","examen":"DEF 2024","mention":""},"6662":{"prenom":"Fatoumata Oulé","nom":"KEITA","sexe":"F","statut":"REG","ecole":"","option_type":"CLASS","centre_examen":"REG FARABALA 2È C","cap":"FARABALA","academie":"ACADEMIE D'ENSEIGNEMENT DE KITA","examen":"DEF 2024","mention":""},"6806":{"prenom":"Kadiatou","nom":"KEITA","sexe":"F","statut":"REG","ecole":"","option_type":"CLASS","centre_examen":"REG FARABALA 2È C","cap":"FARABALA","academie":"ACADEMIE D'ENSEIGNEMENT DE KITA","examen":"DEF 2024","mention":""},"7031":{"prenom":"Makan Moussou Dite Sato","nom":"KEITA","sexe":"F","statut":"REG","ecole":"","option_type":"CLASS","centre_examen":"REG FARABALA 2È C","cap":"FARABALA","academie":"ACADEMIE D'ENSEIGNEMENT DE KITA","examen":"DEF 2024","mention":""},"8821":{"prenom":"Mamadou","nom":"SAMAKE","sexe":"M","statut":"REG","ecole":"","option_type":"CLASS","centre_examen":"REG FARABALA 2È C","cap":"FARABALA","academie":"ACADEMIE D'ENSEIGNEMENT DE KITA","examen":"DEF 2024","mention":""},"9026":{"prenom":"Bougouge","nom":"SANOGO","sexe":"M","statut":"REG","ecole":"","option_type":"CLASS","centre_examen":"REG FARABALA 2È C","cap":"FARABALA","academie":"ACADEMIE D'ENSEIGNEMENT DE KITA","examen":"DEF 2024","mention":""},"9046":{"prenom":"Mahamadou Bassiri","nom":"SANOGO","sexe":"M","statut":"REG","ecole":"","option_type":"CLASS","centre_examen":"REG FARABALA 2È C","cap":"FARABALA","academie":"ACADEMIE D'ENSEIGNEMENT DE KITA","examen":"DEF 2024","mention":""},"9061":{"prenom":"Yacouba","nom":"SANOGO","sexe":"M","statut":"REG","ecole":"","option_type":"CLASS","centre_examen":"REG FARABALA 2È C","cap":"FARABALA","academie":"ACADEMIE D'ENSEIGNEMENT DE KITA","examen":"DEF 2024","mention":""},"9196":{"prenom":"Cheick Omar Djiguidian","nom":"SIDIBE","sexe":"M","statut":"REG","ecole":"","option_type":"CLASS","centre_examen":"REG FARABALA 2È C","cap":"FARABALA","academie":"ACADEMIE D'ENSEIGNEMENT DE KITA","examen":"DEF 2024","mention":""},"9429":{"prenom":"Mamadou","nom":"SIDIBE","sexe":"M","statut":"REG","ecole":"","option_type":"CLASS","centre_examen":"REG FARABALA 2È C","cap":"FARABALA","academie":"ACADEMIE D'ENSEIGNEMENT DE KITA","examen":"DEF 2024","mention":""},"10435":{"prenom":"Sékou","nom":"SISSOKO","sexe":"M","statut":"REG","ecole":"","option_type":"CLASS","centre_examen":"REG FARABALA 2È C","cap":"FARABALA","academie":"ACADEMIE D'ENSEIGNEMENT DE KITA","examen":"DEF 2024","mention":""},"10735":{"prenom":"Salimatou","nom":"SYLLA","sexe":"F","statut":"REG","ecole":"","option_type":"CLASS","centre_examen":"REG FARABALA 2È C","cap":"FARABALA","academie":"ACADEMIE D'ENSEIGNEMENT DE KITA","examen":"DEF 2024","mention":""},"10753":{"prenom":"Aboubakar Ak","nom":"TANGARA","sexe":"M","statut":"REG","ecole":"","option_type":"CLASS","centre_examen":"REG FARABALA 2È C","cap":"FARABALA","academie":"ACADEMIE D'ENSEIGNEMENT DE KITA","examen":"DEF 2024","mention":""},"10830":{"prenom":"Adama B.","nom":"TOUNKARA","sexe":"M","statut":"REG","ecole":"","option_type":"CLASS","centre_examen":"REG FARABALA 2È C","cap":"FARABALA","academie":"ACADEMIE D'ENSEIGNEMENT DE KITA","examen":"DEF 2024","mention":""},"10831":{"prenom":"Adama D.","nom":"TOUNKARA","sexe":"M","statut":"REG","ecole":"","option_type":"CLASS","centre_examen":"REG FARABALA 2È C","cap":"FARABALA","academie":"ACADEMIE D'ENSEIGNEMENT DE KITA","examen":"DEF 2024","mention":""},"10859":{"prenom":"Assétou","nom":"","sexe":"M","statut":"REG","ecole":"","option_type":"CLASS","centre_examen":"REG FARABALA 2È C","cap":"FARABALA","academie":"ACADEMIE D'ENSEIGNEMENT DE KITA","examen":"DEF 2024","mention":""},"10861":{"prenom":"Bakou","nom":"TOUNKARA","sexe":"M","statut":"REG","ecole":"","option_type":"CLASS","centre_examen":"REG FARABALA 2È C","cap":"FARABALA","academie":"ACADEMIE D'ENSEIGNEMENT DE KITA","examen":"DEF 2024","mention":""},"10877":{"prenom":"Boune","nom":"TOUNKARA","sexe":"M","statut":"REG","ecole":"","option_type":"CLASS","centre_examen":"REG FARABALA 2È C","cap":"FARABALA","academie":"ACADEMIE D'ENSEIGNEMENT DE KITA","examen":"DEF 2024","mention":""},"11442":{"prenom":"Daby","nom":"TRAORE","sexe":"M","statut":"REG","ecole":"","option_type":"CLASS","centre_examen":"REG FARABALA 2È C","cap":"FARABALA","academie":"ACADEMIE D'ENSEIGNEMENT DE KITA","examen":"DEF 2024","mention":""},"11529":{"prenom":"Fatoumata Dite Seba","nom":"TRAORE","sexe":"F","statut":"REG","ecole":"","option_type":"CLASS","centre_examen":"REG FARABALA 2È C","cap":"FARABALA","academie":"ACADEMIE D'ENSEIGNEMENT DE KITA","examen":"DEF 2024","mention":""},"11640":{"prenom":"Kokoun","nom":"TRAORE","sexe":"M","statut":"REG","ecole":"","option_type":"CLASS","centre_examen":"REG FARABALA 2È C","cap":"FARABALA","academie":"ACADEMIE D'ENSEIGNEMENT DE KITA","examen":"DEF 2024","mention":""},"11699":{"prenom":"Mamory","nom":"TRAORE","sexe":"F","statut":"REG","ecole":"","option_type":"CLASS","centre_examen":"REG FARABALA 2È C","cap":"FARABALA","academie":"ACADEMIE D'ENSEIGNEMENT DE KITA","examen":"DEF 2024","mention":""},"11798":{"prenom":"Rahama","nom":"TRAORE","sexe":"F","statut":"REG","ecole":"","option_type":"CLASS","centre_examen":"REG FARABALA 2È C","cap":"FARABALA","academie":"ACADEMIE D'ENSEIGNEMENT DE KITA","examen":"DEF 2024","mention":""}}