{"69":{"prenom":"Achei kna","nom":"AGWADOSSANE 19/ 03/ 1999CLCLASSIQUECL- TIDERMENE- AE- MKAI KADEWANE","sexe":"","statut":"REG","ecole":"","option_type":"CLASS","centre_examen":"","cap":"","academie":"ACADEMIE D'ENSEIGNEMENT DE MENAKA","examen":"DEF 2024","mention":""},"71":{"prenom":"Mar i am","nom":"ALHASSANE 25/ 06/ 2008REGCLASSIQUEI KADEWANES/ CI KADEWANE","sexe":"","statut":"REG","ecole":"","option_type":"CLASS","centre_examen":"","cap":"","academie":"ACADEMIE D'ENSEIGNEMENT DE MENAKA","examen":"DEF 2024","mention":""},"72":{"prenom":"Seydou","nom":"CHAÏBOU 30/ 04/ 2006REGCLASSIQUEI KADEWANES/ CI KADEWANE","sexe":"","statut":"REG","ecole":"","option_type":"CLASS","centre_examen":"","cap":"","academie":"ACADEMIE D'ENSEIGNEMENT DE MENAKA","examen":"DEF 2024","mention":""},"79":{"prenom":"Adi zat ou","nom":"SEYDOU 31/ 12/ 2007REGCLASSIQUEI KADEWANES/ CI KADEWANE","sexe":"","statut":"REG","ecole":"","option_type":"CLASS","centre_examen":"","cap":"","academie":"ACADEMIE D'ENSEIGNEMENT DE MENAKA","examen":"DEF 2024","mention":""},"84":{"prenom":"Al housseyni","nom":"ALKASSOUM 31/ 12/ 1983CLCLASSIQUECL- TIDERMENE- AE- MKAI KADEWANE","sexe":"","statut":"REG","ecole":"","option_type":"CLASS","centre_examen":"","cap":"","academie":"ACADEMIE D'ENSEIGNEMENT DE MENAKA","examen":"DEF 2024","mention":""},"87":{"prenom":"Ousmane","nom":"AGAGALY 31/ 12/ 1998CLCLASSIQUECL- TIDERMENE- AE- MKAI KADEWANE","sexe":"","statut":"REG","ecole":"","option_type":"CLASS","centre_examen":"","cap":"","academie":"ACADEMIE D'ENSEIGNEMENT DE MENAKA","examen":"DEF 2024","mention":""},"96":{"prenom":"Abdoul aye","nom":"AGRABAH 18/ 11/ 2009REGCLASSIQUEI KADEWANES/ CI KADEWANE","sexe":"","statut":"REG","ecole":"","option_type":"CLASS","centre_examen":"","cap":"","academie":"ACADEMIE D'ENSEIGNEMENT DE MENAKA","examen":"DEF 2024","mention":""},"99":{"prenom":"Thi er no Mavi atDaIALLO 19/ 10/ 2005REGCLASSIQUEI KADEWANES/","nom":"CI KADEWANE","sexe":"","statut":"REG","ecole":"","option_type":"CLASS","centre_examen":"","cap":"","academie":"ACADEMIE D'ENSEIGNEMENT DE MENAKA","examen":"DEF 2024","mention":""},"106":{"prenom":"Mar i am I ssouf","nom":"MAÏGA 15/ 12/ 2005REGCLASSIQUEI KADEWANES/ CI KADEWANE","sexe":"","statut":"REG","ecole":"","option_type":"CLASS","centre_examen":"","cap":"","academie":"ACADEMIE D'ENSEIGNEMENT DE MENAKA","examen":"DEF 2024","mention":""},"108":{"prenom":"Mar i am","nom":"SOULEYMANE 31/ 12/ 2004REGCLASSIQUEI KADEWANES/ CI KADEWANE","sexe":"","statut":"REG","ecole":"","option_type":"CLASS","centre_examen":"","cap":"","academie":"ACADEMIE D'ENSEIGNEMENT DE MENAKA","examen":"DEF 2024","mention":""},"110":{"prenom":"I br ahi m Ag","nom":"TAJOUDEN 04/ 03/ 2007REGCLASSIQUEI KADEWANES/ CI KADEWANE","sexe":"","statut":"REG","ecole":"","option_type":"CLASS","centre_examen":"","cap":"","academie":"ACADEMIE D'ENSEIGNEMENT DE MENAKA","examen":"DEF 2024","mention":""},"121":{"prenom":"Fadi mat","nom":"WTSWAYLAME 31/ 12/ 2000CLCLASSIQUECL- TIDERMENE- AE- MKAI KADEWANE","sexe":"","statut":"REG","ecole":"","option_type":"CLASS","centre_examen":"","cap":"","academie":"ACADEMIE D'ENSEIGNEMENT DE MENAKA","examen":"DEF 2024","mention":""},"122":{"prenom":"Ousmana","nom":"ZEINEDINE 14/ 04/ 2004REGCLASSIQUEI KADEWANES/ CI KADEWANE","sexe":"","statut":"REG","ecole":"","option_type":"CLASS","centre_examen":"","cap":"","academie":"ACADEMIE D'ENSEIGNEMENT DE MENAKA","examen":"DEF 2024","mention":""},"434":{"prenom":"Mar i am","nom":"ADAMOU 01/ 01/ 2003CL CLASSI QUE I KADEWANE S/ C I KADEWANE","sexe":"","statut":"REG","ecole":"","option_type":"CLASS","centre_examen":"","cap":"","academie":"ACADEMIE D'ENSEIGNEMENT DE MENAKA","examen":"DEF 2024","mention":""},"125":{"prenom":"","nom":"MAHAMANEABDOULAYE 01/ 01/ 2010 REGCLASSIQUE","sexe":"","statut":"REG","ecole":"","option_type":"CLASS","centre_examen":"","cap":"","academie":"ACADEMIE D'ENSEIGNEMENT DE MENAKA","examen":"DEF 2024","mention":""},"128":{"prenom":"","nom":"AICHATAWALETADASS 31/ 12/ 2009 REGCLASSIQUE","sexe":"","statut":"REG","ecole":"","option_type":"CLASS","centre_examen":"","cap":"","academie":"ACADEMIE D'ENSEIGNEMENT DE MENAKA","examen":"DEF 2024","mention":""},"132":{"prenom":"Agui di d","nom":"AGMAHAMAD 31/ 12/ 2002 CLCLASSIQUE","sexe":"","statut":"REG","ecole":"","option_type":"CLASS","centre_examen":"","cap":"","academie":"ACADEMIE D'ENSEIGNEMENT DE MENAKA","examen":"DEF 2024","mention":""},"133":{"prenom":"","nom":"ABDOULAYEAGALI 31/ 12/ 2006 REGCLASSIQUE","sexe":"","statut":"REG","ecole":"","option_type":"CLASS","centre_examen":"","cap":"","academie":"ACADEMIE D'ENSEIGNEMENT DE MENAKA","examen":"DEF 2024","mention":""},"135":{"prenom":"","nom":"AGALYAGAGUISSA 31/ 12/ 2007 REGCLASSIQUE","sexe":"","statut":"REG","ecole":"","option_type":"CLASS","centre_examen":"","cap":"","academie":"ACADEMIE D'ENSEIGNEMENT DE MENAKA","examen":"DEF 2024","mention":""},"138":{"prenom":"Agui ssa Ag","nom":"AHMED 31/ 12/ 1989 CLCLASSIQUE","sexe":"","statut":"REG","ecole":"","option_type":"CLASS","centre_examen":"","cap":"","academie":"ACADEMIE D'ENSEIGNEMENT DE MENAKA","examen":"DEF 2024","mention":""},"139":{"prenom":"Hamadi Si di","nom":"AHMED 31/ 12/ 2009 CLCLASSIQUE","sexe":"","statut":"REG","ecole":"","option_type":"CLASS","centre_examen":"","cap":"","academie":"ACADEMIE D'ENSEIGNEMENT DE MENAKA","examen":"DEF 2024","mention":""},"151":{"prenom":"","nom":"OUSMANEAGALMOCTAR 15/ 07/ 2005 REGCLASSIQUE","sexe":"","statut":"REG","ecole":"","option_type":"CLASS","centre_examen":"","cap":"","academie":"ACADEMIE D'ENSEIGNEMENT DE MENAKA","examen":"DEF 2024","mention":""},"152":{"prenom":"","nom":"SAYATWALETALMOCTAR 26/ 02/ 2008 REGCLASSIQUE","sexe":"","statut":"REG","ecole":"","option_type":"CLASS","centre_examen":"","cap":"","academie":"ACADEMIE D'ENSEIGNEMENT DE MENAKA","examen":"DEF 2024","mention":""},"153":{"prenom":"","nom":"IBRAHIM ALMOUSTAPHA 01/ 12/ 2007 REGCLASSIQUE","sexe":"","statut":"REG","ecole":"","option_type":"CLASS","centre_examen":"","cap":"","academie":"ACADEMIE D'ENSEIGNEMENT DE MENAKA","examen":"DEF 2024","mention":""},"154":{"prenom":"","nom":"ZALIFAALOUSSEINY 22/ 01/ 2004 REGCLASSIQUE","sexe":"","statut":"REG","ecole":"","option_type":"CLASS","centre_examen":"","cap":"","academie":"ACADEMIE D'ENSEIGNEMENT DE MENAKA","examen":"DEF 2024","mention":""},"155":{"prenom":"","nom":"ADAMOUAMADOU 31/ 12/ 2003 REGCLASSIQUE","sexe":"","statut":"REG","ecole":"","option_type":"CLASS","centre_examen":"","cap":"","academie":"ACADEMIE D'ENSEIGNEMENT DE MENAKA","examen":"DEF 2024","mention":""},"158":{"prenom":"","nom":"HAWAWALETAZOUNZOUNO 31/ 12/ 2010 REGCLASSIQUE","sexe":"","statut":"REG","ecole":"","option_type":"CLASS","centre_examen":"","cap":"","academie":"ACADEMIE D'ENSEIGNEMENT DE MENAKA","examen":"DEF 2024","mention":""},"160":{"prenom":"","nom":"MOHAMEDAGBATTAYE 31/ 12/ 2007 REGCLASSIQUE","sexe":"","statut":"REG","ecole":"","option_type":"CLASS","centre_examen":"","cap":"","academie":"ACADEMIE D'ENSEIGNEMENT DE MENAKA","examen":"DEF 2024","mention":""},"161":{"prenom":"","nom":"ISSOUFAGBOUJEN 31/ 12/ 2007 REGCLASSIQUE","sexe":"","statut":"REG","ecole":"","option_type":"CLASS","centre_examen":"","cap":"","academie":"ACADEMIE D'ENSEIGNEMENT DE MENAKA","examen":"DEF 2024","mention":""},"163":{"prenom":"","nom":"CHEICKOUMARDIARRA 24/ 05/ 2010 REGCLASSIQUE","sexe":"","statut":"REG","ecole":"","option_type":"CLASS","centre_examen":"","cap":"","academie":"ACADEMIE D'ENSEIGNEMENT DE MENAKA","examen":"DEF 2024","mention":""},"164":{"prenom":"","nom":"MOUSSAAGHABIDE 31/ 12/ 2005 REGCLASSIQUE","sexe":"","statut":"REG","ecole":"","option_type":"CLASS","centre_examen":"","cap":"","academie":"ACADEMIE D'ENSEIGNEMENT DE MENAKA","examen":"DEF 2024","mention":""},"166":{"prenom":"","nom":"LAILLAWALETHAIMOUD 12/ 01/ 2010 REGCLASSIQUE","sexe":"","statut":"REG","ecole":"","option_type":"CLASS","centre_examen":"","cap":"","academie":"ACADEMIE D'ENSEIGNEMENT DE MENAKA","examen":"DEF 2024","mention":""},"169":{"prenom":"","nom":"ZAINAWTI BILAL 31/ 12/ 2007 REGCLASSIQUE","sexe":"","statut":"REG","ecole":"","option_type":"CLASS","centre_examen":"","cap":"","academie":"ACADEMIE D'ENSEIGNEMENT DE MENAKA","examen":"DEF 2024","mention":""},"174":{"prenom":"","nom":"MARIAMAI BRAHIM 18/ 06/ 2007 REGCLASSIQUE","sexe":"","statut":"REG","ecole":"","option_type":"CLASS","centre_examen":"","cap":"","academie":"ACADEMIE D'ENSEIGNEMENT DE MENAKA","examen":"DEF 2024","mention":""},"176":{"prenom":"","nom":"AGAICHATAI DOUAL 25/ 12/ 2005 REGCLASSIQUE","sexe":"","statut":"REG","ecole":"","option_type":"CLASS","centre_examen":"","cap":"","academie":"ACADEMIE D'ENSEIGNEMENT DE MENAKA","examen":"DEF 2024","mention":""},"177":{"prenom":"","nom":"ALHASSANEI DOUAL 11/ 10/ 2008 REGCLASSIQUE","sexe":"","statut":"REG","ecole":"","option_type":"CLASS","centre_examen":"","cap":"","academie":"ACADEMIE D'ENSEIGNEMENT DE MENAKA","examen":"DEF 2024","mention":""},"179":{"prenom":"","nom":"ZEINABOUI DOUAL 18/ 02/ 2006 REGCLASSIQUE","sexe":"","statut":"REG","ecole":"","option_type":"CLASS","centre_examen":"","cap":"","academie":"ACADEMIE D'ENSEIGNEMENT DE MENAKA","examen":"DEF 2024","mention":""},"182":{"prenom":"","nom":"ABIDINEAGI MANINE 31/ 12/ 2008 REGCLASSIQUE","sexe":"","statut":"REG","ecole":"","option_type":"CLASS","centre_examen":"","cap":"","academie":"ACADEMIE D'ENSEIGNEMENT DE MENAKA","examen":"DEF 2024","mention":""},"183":{"prenom":"","nom":"ABOUBACRINEAGIMIMI 29/ 02/ 2008 REGCLASSIQUE","sexe":"","statut":"REG","ecole":"","option_type":"CLASS","centre_examen":"","cap":"","academie":"ACADEMIE D'ENSEIGNEMENT DE MENAKA","examen":"DEF 2024","mention":""},"186":{"prenom":"","nom":"AISSATAMAHAMANE 10/ 04/ 2008 REGCLASSIQUE","sexe":"","statut":"REG","ecole":"","option_type":"CLASS","centre_examen":"","cap":"","academie":"ACADEMIE D'ENSEIGNEMENT DE MENAKA","examen":"DEF 2024","mention":""},"187":{"prenom":"","nom":"ABDOULAYEAGMOHAMED 31/ 12/ 2008 REGCLASSIQUE","sexe":"","statut":"REG","ecole":"","option_type":"CLASS","centre_examen":"","cap":"","academie":"ACADEMIE D'ENSEIGNEMENT DE MENAKA","examen":"DEF 2024","mention":""},"188":{"prenom":"","nom":"AHMOUDOUAGMOHAMED 29/ 06/ 2007 REGCLASSIQUE","sexe":"","statut":"REG","ecole":"","option_type":"CLASS","centre_examen":"","cap":"","academie":"ACADEMIE D'ENSEIGNEMENT DE MENAKA","examen":"DEF 2024","mention":""},"189":{"prenom":"","nom":"ARAWDATWALETMOHAMED 31/ 12/ 2006 REGCLASSIQUE","sexe":"","statut":"REG","ecole":"","option_type":"CLASS","centre_examen":"","cap":"","academie":"ACADEMIE D'ENSEIGNEMENT DE MENAKA","examen":"DEF 2024","mention":""},"190":{"prenom":"","nom":"RAHAMAWALETMOHAMED 31/ 12/ 2003 REGCLASSIQUE","sexe":"","statut":"REG","ecole":"","option_type":"CLASS","centre_examen":"","cap":"","academie":"ACADEMIE D'ENSEIGNEMENT DE MENAKA","examen":"DEF 2024","mention":""},"191":{"prenom":"","nom":"ARAHATWALETMOHAMED 31/ 12/ 2005 REGCLASSIQUE","sexe":"","statut":"REG","ecole":"","option_type":"CLASS","centre_examen":"","cap":"","academie":"ACADEMIE D'ENSEIGNEMENT DE MENAKA","examen":"DEF 2024","mention":""},"192":{"prenom":"","nom":"HOUSSEINIMOUNKAILA 31/ 12/ 2007 REGCLASSIQUE","sexe":"","statut":"REG","ecole":"","option_type":"CLASS","centre_examen":"","cap":"","academie":"ACADEMIE D'ENSEIGNEMENT DE MENAKA","examen":"DEF 2024","mention":""},"194":{"prenom":"","nom":"MAHAMADMOUSSA 21/ 06/ 2010 REGCLASSIQUE","sexe":"","statut":"REG","ecole":"","option_type":"CLASS","centre_examen":"","cap":"","academie":"ACADEMIE D'ENSEIGNEMENT DE MENAKA","examen":"DEF 2024","mention":""},"195":{"prenom":"","nom":"MAIMOUNAMOUSSA 17/ 02/ 2006 REGCLASSIQUE","sexe":"","statut":"REG","ecole":"","option_type":"CLASS","centre_examen":"","cap":"","academie":"ACADEMIE D'ENSEIGNEMENT DE MENAKA","examen":"DEF 2024","mention":""},"198":{"prenom":"","nom":"ANOURADINERADIYOUNE 31/ 12/ 2007 REGCLASSIQUE","sexe":"","statut":"REG","ecole":"","option_type":"CLASS","centre_examen":"","cap":"","academie":"ACADEMIE D'ENSEIGNEMENT DE MENAKA","examen":"DEF 2024","mention":""},"200":{"prenom":"OUMARAGSIDIMOHAMED31/ 12/ 2007","nom":"REGCLASSIQUE","sexe":"","statut":"REG","ecole":"","option_type":"CLASS","centre_examen":"","cap":"","academie":"ACADEMIE D'ENSEIGNEMENT DE MENAKA","examen":"DEF 2024","mention":""},"202":{"prenom":"","nom":"OUMARAGSOULEYMANE 31/ 12/ 2007 REGCLASSIQUE","sexe":"","statut":"REG","ecole":"","option_type":"CLASS","centre_examen":"","cap":"","academie":"ACADEMIE D'ENSEIGNEMENT DE MENAKA","examen":"DEF 2024","mention":""},"203":{"prenom":"","nom":"ABDOULKARIM AGTANIMINAK 31/ 12/ 2008 REGCLASSIQUE","sexe":"","statut":"REG","ecole":"","option_type":"CLASS","centre_examen":"","cap":"","academie":"ACADEMIE D'ENSEIGNEMENT DE MENAKA","examen":"DEF 2024","mention":""},"204":{"prenom":"","nom":"ALHOUSSEINIAGYACOUBA 31/ 12/ 2007 REGCLASSIQUE","sexe":"","statut":"REG","ecole":"","option_type":"CLASS","centre_examen":"","cap":"","academie":"ACADEMIE D'ENSEIGNEMENT DE MENAKA","examen":"DEF 2024","mention":""},"206":{"prenom":"","nom":"ABDOULHAYOUAGABDOULAYE 31/ 12/ 2009 REGCLASSIQUE","sexe":"","statut":"REG","ecole":"","option_type":"CLASS","centre_examen":"","cap":"","academie":"ACADEMIE D'ENSEIGNEMENT DE MENAKA","examen":"DEF 2024","mention":""},"208":{"prenom":"","nom":"ASSALIM AGABDOULAYE 12/ 01/ 2007 REGCLASSIQUE","sexe":"","statut":"REG","ecole":"","option_type":"CLASS","centre_examen":"","cap":"","academie":"ACADEMIE D'ENSEIGNEMENT DE MENAKA","examen":"DEF 2024","mention":""},"209":{"prenom":"","nom":"ISSOUFAGABDOULAYE 31/ 12/ 2007 REGCLASSIQUE","sexe":"","statut":"REG","ecole":"","option_type":"CLASS","centre_examen":"","cap":"","academie":"ACADEMIE D'ENSEIGNEMENT DE MENAKA","examen":"DEF 2024","mention":""},"210":{"prenom":"","nom":"MOHAMEDABDOURAHAM 31/ 12/ 2007 REGCLASSIQUE","sexe":"","statut":"REG","ecole":"","option_type":"CLASS","centre_examen":"","cap":"","academie":"ACADEMIE D'ENSEIGNEMENT DE MENAKA","examen":"DEF 2024","mention":""},"211":{"prenom":"","nom":"MOHAMEDAGABDOURAZACK 15/ 02/ 2008 REGCLASSIQUE","sexe":"","statut":"REG","ecole":"","option_type":"CLASS","centre_examen":"","cap":"","academie":"ACADEMIE D'ENSEIGNEMENT DE MENAKA","examen":"DEF 2024","mention":""},"212":{"prenom":"","nom":"AMINATOUABDOURHAMA 12/ 11/ 2007 REGCLASSIQUE","sexe":"","statut":"REG","ecole":"","option_type":"CLASS","centre_examen":"","cap":"","academie":"ACADEMIE D'ENSEIGNEMENT DE MENAKA","examen":"DEF 2024","mention":""},"213":{"prenom":"","nom":"IBRAHIM AGABDOUSSALAM03/ 09/ 2010 REGCLASSIQUE","sexe":"","statut":"REG","ecole":"","option_type":"CLASS","centre_examen":"","cap":"","academie":"ACADEMIE D'ENSEIGNEMENT DE MENAKA","examen":"DEF 2024","mention":""},"214":{"prenom":"","nom":"HAMAD- ASSALEHABOUBACRINE 31/ 12/ 2006 REGCLASSIQUE","sexe":"","statut":"REG","ecole":"","option_type":"CLASS","centre_examen":"","cap":"","academie":"ACADEMIE D'ENSEIGNEMENT DE MENAKA","examen":"DEF 2024","mention":""},"216":{"prenom":"","nom":"MASSASSAWALETACHEICK 31/ 12/ 2009 REGCLASSIQUE","sexe":"","statut":"REG","ecole":"","option_type":"CLASS","centre_examen":"","cap":"","academie":"ACADEMIE D'ENSEIGNEMENT DE MENAKA","examen":"DEF 2024","mention":""},"218":{"prenom":"","nom":"FATOUMATAADA 31/ 12/ 2005 REGCLASSIQUE","sexe":"","statut":"REG","ecole":"","option_type":"CLASS","centre_examen":"","cap":"","academie":"ACADEMIE D'ENSEIGNEMENT DE MENAKA","examen":"DEF 2024","mention":""},"220":{"prenom":"","nom":"LALAAGAMNA 18/ 02/ 2009 REGCLASSIQUE","sexe":"","statut":"REG","ecole":"","option_type":"CLASS","centre_examen":"","cap":"","academie":"ACADEMIE D'ENSEIGNEMENT DE MENAKA","examen":"DEF 2024","mention":""},"221":{"prenom":"","nom":"BOUBACARAGAGUISSA 31/ 12/ 2006 REGCLASSIQUE","sexe":"","statut":"REG","ecole":"","option_type":"CLASS","centre_examen":"","cap":"","academie":"ACADEMIE D'ENSEIGNEMENT DE MENAKA","examen":"DEF 2024","mention":""},"222":{"prenom":"","nom":"HALBERAGUISSA 31/ 12/ 2008 REGCLASSIQUE","sexe":"","statut":"REG","ecole":"","option_type":"CLASS","centre_examen":"","cap":"","academie":"ACADEMIE D'ENSEIGNEMENT DE MENAKA","examen":"DEF 2024","mention":""},"223":{"prenom":"","nom":"OUSMANEAGAGUISSA 09/ 11/ 2008 REGCLASSIQUE","sexe":"","statut":"REG","ecole":"","option_type":"CLASS","centre_examen":"","cap":"","academie":"ACADEMIE D'ENSEIGNEMENT DE MENAKA","examen":"DEF 2024","mention":""},"225":{"prenom":"","nom":"HABIAHAMADOU 31/ 12/ 2005 REGCLASSIQUE","sexe":"","statut":"REG","ecole":"","option_type":"CLASS","centre_examen":"","cap":"","academie":"ACADEMIE D'ENSEIGNEMENT DE MENAKA","examen":"DEF 2024","mention":""},"226":{"prenom":"","nom":"AMMAAGAHMAD 31/ 12/ 2008 REGCLASSIQUE","sexe":"","statut":"REG","ecole":"","option_type":"CLASS","centre_examen":"","cap":"","academie":"ACADEMIE D'ENSEIGNEMENT DE MENAKA","examen":"DEF 2024","mention":""},"227":{"prenom":"","nom":"MOHAMEDAGAHMAD 01/ 12/ 2007 REGCLASSIQUE","sexe":"","statut":"REG","ecole":"","option_type":"CLASS","centre_examen":"","cap":"","academie":"ACADEMIE D'ENSEIGNEMENT DE MENAKA","examen":"DEF 2024","mention":""},"228":{"prenom":"","nom":"YACOUBAAGAHMADOU 31/ 12/ 2008 REGCLASSIQUE","sexe":"","statut":"REG","ecole":"","option_type":"CLASS","centre_examen":"","cap":"","academie":"ACADEMIE D'ENSEIGNEMENT DE MENAKA","examen":"DEF 2024","mention":""},"229":{"prenom":"","nom":"ABDOURAHMANEAHMED 31/ 12/ 2006 REGCLASSIQUE","sexe":"","statut":"REG","ecole":"","option_type":"CLASS","centre_examen":"","cap":"","academie":"ACADEMIE D'ENSEIGNEMENT DE MENAKA","examen":"DEF 2024","mention":""},"230":{"prenom":"","nom":"IBRAHIM AGAHMED 02/ 08/ 2005 REGCLASSIQUE","sexe":"","statut":"REG","ecole":"","option_type":"CLASS","centre_examen":"","cap":"","academie":"ACADEMIE D'ENSEIGNEMENT DE MENAKA","examen":"DEF 2024","mention":""},"231":{"prenom":"","nom":"IBRAHIM AGAHMED 31/ 12/ 2006 REGCLASSIQUE","sexe":"","statut":"REG","ecole":"","option_type":"CLASS","centre_examen":"","cap":"","academie":"ACADEMIE D'ENSEIGNEMENT DE MENAKA","examen":"DEF 2024","mention":""},"232":{"prenom":"","nom":"MOUSSAAGAHMED 14/ 02/ 2008 REGCLASSIQUE","sexe":"","statut":"REG","ecole":"","option_type":"CLASS","centre_examen":"","cap":"","academie":"ACADEMIE D'ENSEIGNEMENT DE MENAKA","examen":"DEF 2024","mention":""},"235":{"prenom":"","nom":"YOUNOUSSEAGALHASSANE 31/ 12/ 2007 REGCLASSIQUE","sexe":"","statut":"REG","ecole":"","option_type":"CLASS","centre_examen":"","cap":"","academie":"ACADEMIE D'ENSEIGNEMENT DE MENAKA","examen":"DEF 2024","mention":""},"236":{"prenom":"","nom":"AISSAALI 28/ 07/ 2008 REGCLASSIQUE","sexe":"","statut":"REG","ecole":"","option_type":"CLASS","centre_examen":"","cap":"","academie":"ACADEMIE D'ENSEIGNEMENT DE MENAKA","examen":"DEF 2024","mention":""},"237":{"prenom":"","nom":"MARIAMWALETALMAIMOUNE 31/ 12/ 2009 REGCLASSIQUE","sexe":"","statut":"REG","ecole":"","option_type":"CLASS","centre_examen":"","cap":"","academie":"ACADEMIE D'ENSEIGNEMENT DE MENAKA","examen":"DEF 2024","mention":""},"238":{"prenom":"","nom":"EGLASSEAGALMOMINE 31/ 12/ 2007 REGCLASSIQUE","sexe":"","statut":"REG","ecole":"","option_type":"CLASS","centre_examen":"","cap":"","academie":"ACADEMIE D'ENSEIGNEMENT DE MENAKA","examen":"DEF 2024","mention":""},"239":{"prenom":"","nom":"MAHMOUDAGALMOUSTAKIN 17/ 08/ 2008 REGCLASSIQUE","sexe":"","statut":"REG","ecole":"","option_type":"CLASS","centre_examen":"","cap":"","academie":"ACADEMIE D'ENSEIGNEMENT DE MENAKA","examen":"DEF 2024","mention":""},"241":{"prenom":"","nom":"ALHOUSSEINIAGARASSOUL 10/ 04/ 2008 REGCLASSIQUE","sexe":"","statut":"REG","ecole":"","option_type":"CLASS","centre_examen":"","cap":"","academie":"ACADEMIE D'ENSEIGNEMENT DE MENAKA","examen":"DEF 2024","mention":""},"242":{"prenom":"","nom":"HAMAD- ASSALEHASSALATE 31/ 12/ 2010 REGCLASSIQUE","sexe":"","statut":"REG","ecole":"","option_type":"CLASS","centre_examen":"","cap":"","academie":"ACADEMIE D'ENSEIGNEMENT DE MENAKA","examen":"DEF 2024","mention":""},"244":{"prenom":"","nom":"FADIMATWALETASSANHORI 31/ 12/ 2009 REGCLASSIQUE","sexe":"","statut":"REG","ecole":"","option_type":"CLASS","centre_examen":"","cap":"","academie":"ACADEMIE D'ENSEIGNEMENT DE MENAKA","examen":"DEF 2024","mention":""},"246":{"prenom":"","nom":"HAWAAZOUBER 11/ 05/ 2007 REGCLASSIQUE","sexe":"","statut":"REG","ecole":"","option_type":"CLASS","centre_examen":"","cap":"","academie":"ACADEMIE D'ENSEIGNEMENT DE MENAKA","examen":"DEF 2024","mention":""},"247":{"prenom":"","nom":"ISSSOUFAOULDBABA 31/ 12/ 2005 REGCLASSIQUE","sexe":"","statut":"REG","ecole":"","option_type":"CLASS","centre_examen":"","cap":"","academie":"ACADEMIE D'ENSEIGNEMENT DE MENAKA","examen":"DEF 2024","mention":""},"248":{"prenom":"","nom":"OUMARAGBADY 31/ 12/ 2008 REGCLASSIQUE","sexe":"","statut":"REG","ecole":"","option_type":"CLASS","centre_examen":"","cap":"","academie":"ACADEMIE D'ENSEIGNEMENT DE MENAKA","examen":"DEF 2024","mention":""},"249":{"prenom":"","nom":"LEYLAWALETBAYE 04/ 04/ 2008 REGCLASSIQUE","sexe":"","statut":"REG","ecole":"","option_type":"CLASS","centre_examen":"","cap":"","academie":"ACADEMIE D'ENSEIGNEMENT DE MENAKA","examen":"DEF 2024","mention":""},"254":{"prenom":"","nom":"MOUSSAAGBRAHIM 31/ 12/ 2009 REGCLASSIQUE","sexe":"","statut":"REG","ecole":"","option_type":"CLASS","centre_examen":"","cap":"","academie":"ACADEMIE D'ENSEIGNEMENT DE MENAKA","examen":"DEF 2024","mention":""},"255":{"prenom":"","nom":"ZEINABACHEKOU 31/ 12/ 2007 REGCLASSIQUE","sexe":"","statut":"REG","ecole":"","option_type":"CLASS","centre_examen":"","cap":"","academie":"ACADEMIE D'ENSEIGNEMENT DE MENAKA","examen":"DEF 2024","mention":""},"258":{"prenom":"","nom":"FATOUMATACISSE 26/ 10/ 2010 REGCLASSIQUE","sexe":"","statut":"REG","ecole":"","option_type":"CLASS","centre_examen":"","cap":"","academie":"ACADEMIE D'ENSEIGNEMENT DE MENAKA","examen":"DEF 2024","mention":""},"259":{"prenom":"","nom":"HAMZABOUBACARCISSE 16/ 09/ 2006 REGCLASSIQUE","sexe":"","statut":"REG","ecole":"","option_type":"CLASS","centre_examen":"","cap":"","academie":"ACADEMIE D'ENSEIGNEMENT DE MENAKA","examen":"DEF 2024","mention":""},"260":{"prenom":"","nom":"AMINTADIALLO 31/ 12/ 2008 REGCLASSIQUE","sexe":"","statut":"REG","ecole":"","option_type":"CLASS","centre_examen":"","cap":"","academie":"ACADEMIE D'ENSEIGNEMENT DE MENAKA","examen":"DEF 2024","mention":""},"261":{"prenom":"","nom":"MAHAMADOUDICKO 07/ 09/ 2009 REGCLASSIQUE","sexe":"","statut":"REG","ecole":"","option_type":"CLASS","centre_examen":"","cap":"","academie":"ACADEMIE D'ENSEIGNEMENT DE MENAKA","examen":"DEF 2024","mention":""},"262":{"prenom":"","nom":"MOUSSAI SSOUFDICKO 01/ 08/ 2006 REGCLASSIQUE","sexe":"","statut":"REG","ecole":"","option_type":"CLASS","centre_examen":"","cap":"","academie":"ACADEMIE D'ENSEIGNEMENT DE MENAKA","examen":"DEF 2024","mention":""},"265":{"prenom":"","nom":"FATOUMATAGUINDO 06/ 06/ 2009 REGCLASSIQUE","sexe":"","statut":"REG","ecole":"","option_type":"CLASS","centre_examen":"","cap":"","academie":"ACADEMIE D'ENSEIGNEMENT DE MENAKA","examen":"DEF 2024","mention":""},"266":{"prenom":"","nom":"BARATOUHABIBOU 27/ 07/ 2007 REGCLASSIQUE","sexe":"","statut":"REG","ecole":"","option_type":"CLASS","centre_examen":"","cap":"","academie":"ACADEMIE D'ENSEIGNEMENT DE MENAKA","examen":"DEF 2024","mention":""},"271":{"prenom":"","nom":"FATOUMAHAMADOU 15/ 09/ 2007 REGCLASSIQUE","sexe":"","statut":"REG","ecole":"","option_type":"CLASS","centre_examen":"","cap":"","academie":"ACADEMIE D'ENSEIGNEMENT DE MENAKA","examen":"DEF 2024","mention":""},"274":{"prenom":"","nom":"RAMATAHAMZA 01/ 01/ 2007 REGCLASSIQUE","sexe":"","statut":"REG","ecole":"","option_type":"CLASS","centre_examen":"","cap":"","academie":"ACADEMIE D'ENSEIGNEMENT DE MENAKA","examen":"DEF 2024","mention":""},"275":{"prenom":"","nom":"ALBACHARAGHISSANE 31/ 12/ 2010 REGCLASSIQUE","sexe":"","statut":"REG","ecole":"","option_type":"CLASS","centre_examen":"","cap":"","academie":"ACADEMIE D'ENSEIGNEMENT DE MENAKA","examen":"DEF 2024","mention":""},"276":{"prenom":"","nom":"IDRISSAI BNI 21/ 04/ 2009 REGCLASSIQUE","sexe":"","statut":"REG","ecole":"","option_type":"CLASS","centre_examen":"","cap":"","academie":"ACADEMIE D'ENSEIGNEMENT DE MENAKA","examen":"DEF 2024","mention":""},"277":{"prenom":"","nom":"SALMAWALETI BNI 07/ 11/ 2010 REGCLASSIQUE","sexe":"","statut":"REG","ecole":"","option_type":"CLASS","centre_examen":"","cap":"","academie":"ACADEMIE D'ENSEIGNEMENT DE MENAKA","examen":"DEF 2024","mention":""},"278":{"prenom":"","nom":"ALHASSANEAGI BRAHIM 31/ 12/ 2005 REGCLASSIQUE","sexe":"","statut":"REG","ecole":"","option_type":"CLASS","centre_examen":"","cap":"","academie":"ACADEMIE D'ENSEIGNEMENT DE MENAKA","examen":"DEF 2024","mention":""},"279":{"prenom":"","nom":"ALIOUI BRAHIM 31/ 12/ 2006 REGCLASSIQUE","sexe":"","statut":"REG","ecole":"","option_type":"CLASS","centre_examen":"","cap":"","academie":"ACADEMIE D'ENSEIGNEMENT DE MENAKA","examen":"DEF 2024","mention":""},"281":{"prenom":"","nom":"FATIMATWALETI BRAHIM 31/ 12/ 2007 REGCLASSIQUE","sexe":"","statut":"REG","ecole":"","option_type":"CLASS","centre_examen":"","cap":"","academie":"ACADEMIE D'ENSEIGNEMENT DE MENAKA","examen":"DEF 2024","mention":""},"282":{"prenom":"","nom":"MARDIA IBRAHIM 31/ 12/ 2009 REGCLASSIQUE","sexe":"","statut":"REG","ecole":"","option_type":"CLASS","centre_examen":"","cap":"","academie":"ACADEMIE D'ENSEIGNEMENT DE MENAKA","examen":"DEF 2024","mention":""},"285":{"prenom":"","nom":"AGUISSAI DRISSA 31/ 12/ 2008 REGCLASSIQUE","sexe":"","statut":"REG","ecole":"","option_type":"CLASS","centre_examen":"","cap":"","academie":"ACADEMIE D'ENSEIGNEMENT DE MENAKA","examen":"DEF 2024","mention":""},"286":{"prenom":"","nom":"ISSOUHOUI DRISSA 01/ 02/ 2008 REGCLASSIQUE","sexe":"","statut":"REG","ecole":"","option_type":"CLASS","centre_examen":"","cap":"","academie":"ACADEMIE D'ENSEIGNEMENT DE MENAKA","examen":"DEF 2024","mention":""},"287":{"prenom":"","nom":"SOUREYAI LLIASSOU 07/ 04/ 2007 REGCLASSIQUE","sexe":"","statut":"REG","ecole":"","option_type":"CLASS","centre_examen":"","cap":"","academie":"ACADEMIE D'ENSEIGNEMENT DE MENAKA","examen":"DEF 2024","mention":""},"289":{"prenom":"","nom":"KADIDIA INAKONAK 23/ 06/ 2009 REGCLASSIQUE","sexe":"","statut":"REG","ecole":"","option_type":"CLASS","centre_examen":"","cap":"","academie":"ACADEMIE D'ENSEIGNEMENT DE MENAKA","examen":"DEF 2024","mention":""},"292":{"prenom":"","nom":"HAMZA AG I NTALLA 21/ 08/ 2006","sexe":"","statut":"REG","ecole":"","option_type":"CLASS","centre_examen":"","cap":"","academie":"ACADEMIE D'ENSEIGNEMENT DE MENAKA","examen":"DEF 2024","mention":""},"295":{"prenom":"","nom":"MOHAMED I SSOUF 31/ 12/ 2006","sexe":"","statut":"REG","ecole":"","option_type":"CLASS","centre_examen":"","cap":"","academie":"ACADEMIE D'ENSEIGNEMENT DE MENAKA","examen":"DEF 2024","mention":""},"298":{"prenom":"","nom":"ZEI NABA WALET I SSOUF 07/ 09/ 2006","sexe":"","statut":"REG","ecole":"","option_type":"CLASS","centre_examen":"","cap":"","academie":"ACADEMIE D'ENSEIGNEMENT DE MENAKA","examen":"DEF 2024","mention":""},"299":{"prenom":"","nom":"MOUSSA AG KOTEYE 31/ 12/ 2005","sexe":"","statut":"REG","ecole":"","option_type":"CLASS","centre_examen":"","cap":"","academie":"ACADEMIE D'ENSEIGNEMENT DE MENAKA","examen":"DEF 2024","mention":""},"300":{"prenom":"","nom":"AI CHATA MAHAMADOU 11/ 06/ 2008","sexe":"","statut":"REG","ecole":"","option_type":"CLASS","centre_examen":"","cap":"","academie":"ACADEMIE D'ENSEIGNEMENT DE MENAKA","examen":"DEF 2024","mention":""},"302":{"prenom":"","nom":"AI GAI CHATOU MAHAMANE 28/ 06/ 2009","sexe":"","statut":"REG","ecole":"","option_type":"CLASS","centre_examen":"","cap":"","academie":"ACADEMIE D'ENSEIGNEMENT DE MENAKA","examen":"DEF 2024","mention":""},"303":{"prenom":"","nom":"ZEI NABA MAHAMOUDOU 10/ 09/ 2006","sexe":"","statut":"REG","ecole":"","option_type":"CLASS","centre_examen":"","cap":"","academie":"ACADEMIE D'ENSEIGNEMENT DE MENAKA","examen":"DEF 2024","mention":""},"304":{"prenom":"","nom":"ABDOURAHAMANE MAI GA 30/ 06/ 2010","sexe":"","statut":"REG","ecole":"","option_type":"CLASS","centre_examen":"","cap":"","academie":"ACADEMIE D'ENSEIGNEMENT DE MENAKA","examen":"DEF 2024","mention":""},"305":{"prenom":"","nom":"AGAI CHATOU MAI GA 27/ 03/ 2009","sexe":"","statut":"REG","ecole":"","option_type":"CLASS","centre_examen":"","cap":"","academie":"ACADEMIE D'ENSEIGNEMENT DE MENAKA","examen":"DEF 2024","mention":""},"307":{"prenom":"","nom":"FADI MATA ALMAHDIMAI GA 05/ 10/ 2009","sexe":"","statut":"REG","ecole":"","option_type":"CLASS","centre_examen":"","cap":"","academie":"ACADEMIE D'ENSEIGNEMENT DE MENAKA","examen":"DEF 2024","mention":""},"309":{"prenom":"I","nom":"BRAHI","sexe":"M","statut":"REG","ecole":"","option_type":"CLASS","centre_examen":"","cap":"","academie":"ACADEMIE D'ENSEIGNEMENT DE MENAKA","examen":"DEF 2024","mention":""},"311":{"prenom":"I","nom":"BRAHI","sexe":"M","statut":"REG","ecole":"","option_type":"CLASS","centre_examen":"","cap":"","academie":"ACADEMIE D'ENSEIGNEMENT DE MENAKA","examen":"DEF 2024","mention":""},"313":{"prenom":"","nom":"ADAMOU MAI GA 17/ 03/ 2009","sexe":"","statut":"REG","ecole":"","option_type":"CLASS","centre_examen":"","cap":"","academie":"ACADEMIE D'ENSEIGNEMENT DE MENAKA","examen":"DEF 2024","mention":""},"314":{"prenom":"","nom":"MAI MOUNA MAI GA 14/ 04/ 2008","sexe":"","statut":"REG","ecole":"","option_type":"CLASS","centre_examen":"","cap":"","academie":"ACADEMIE D'ENSEIGNEMENT DE MENAKA","examen":"DEF 2024","mention":""},"315":{"prenom":"","nom":"MOHAMED ABDOUL MAI GA 27/ 10/ 2009","sexe":"","statut":"REG","ecole":"","option_type":"CLASS","centre_examen":"","cap":"","academie":"ACADEMIE D'ENSEIGNEMENT DE MENAKA","examen":"DEF 2024","mention":""},"316":{"prenom":"","nom":"SOUMEI LA MAI GA 31/ 12/ 2010","sexe":"","statut":"REG","ecole":"","option_type":"CLASS","centre_examen":"","cap":"","academie":"ACADEMIE D'ENSEIGNEMENT DE MENAKA","examen":"DEF 2024","mention":""},"317":{"prenom":"","nom":"TAHI ROU MAI GA 19/ 03/ 2008","sexe":"","statut":"REG","ecole":"","option_type":"CLASS","centre_examen":"","cap":"","academie":"ACADEMIE D'ENSEIGNEMENT DE MENAKA","examen":"DEF 2024","mention":""},"318":{"prenom":"","nom":"SALOUHOU MAHAMANE 31/ 12/ 2006","sexe":"","statut":"REG","ecole":"","option_type":"CLASS","centre_examen":"","cap":"","academie":"ACADEMIE D'ENSEIGNEMENT DE MENAKA","examen":"DEF 2024","mention":""},"321":{"prenom":"","nom":"AI CHI TOU WALETMOHAMED 31/ 12/ 2009","sexe":"","statut":"REG","ecole":"","option_type":"CLASS","centre_examen":"","cap":"","academie":"ACADEMIE D'ENSEIGNEMENT DE MENAKA","examen":"DEF 2024","mention":""},"322":{"prenom":"I","nom":"SSOUF AG MOHAMED 25/ 10/ 2009","sexe":"","statut":"REG","ecole":"","option_type":"CLASS","centre_examen":"","cap":"","academie":"ACADEMIE D'ENSEIGNEMENT DE MENAKA","examen":"DEF 2024","mention":""},"324":{"prenom":"","nom":"MARI AME MOHAMED 01/ 01/ 2008","sexe":"","statut":"REG","ecole":"","option_type":"CLASS","centre_examen":"","cap":"","academie":"ACADEMIE D'ENSEIGNEMENT DE MENAKA","examen":"DEF 2024","mention":""},"325":{"prenom":"","nom":"MOUSSA MOHAMED 10/ 09/ 2008","sexe":"","statut":"REG","ecole":"","option_type":"CLASS","centre_examen":"","cap":"","academie":"ACADEMIE D'ENSEIGNEMENT DE MENAKA","examen":"DEF 2024","mention":""},"329":{"prenom":"","nom":"MALAWE WALET MOSSA 01/ 02/ 2009","sexe":"","statut":"REG","ecole":"","option_type":"CLASS","centre_examen":"","cap":"","academie":"ACADEMIE D'ENSEIGNEMENT DE MENAKA","examen":"DEF 2024","mention":""},"331":{"prenom":"","nom":"ALOUSSEI NI MOUSSA 04/ 02/ 2005","sexe":"","statut":"REG","ecole":"","option_type":"CLASS","centre_examen":"","cap":"","academie":"ACADEMIE D'ENSEIGNEMENT DE MENAKA","examen":"DEF 2024","mention":""},"336":{"prenom":"","nom":"KOUBRA SEYDOU 13/ 12/ 2007","sexe":"","statut":"REG","ecole":"","option_type":"CLASS","centre_examen":"","cap":"","academie":"ACADEMIE D'ENSEIGNEMENT DE MENAKA","examen":"DEF 2024","mention":""},"338":{"prenom":"","nom":"AI SSATA WALET SI DI 06/ 05/ 2009","sexe":"","statut":"REG","ecole":"","option_type":"CLASS","centre_examen":"","cap":"","academie":"ACADEMIE D'ENSEIGNEMENT DE MENAKA","examen":"DEF 2024","mention":""},"339":{"prenom":"","nom":"YOUSSOUF AG SI DI 11/ 05/ 2010","sexe":"","statut":"REG","ecole":"","option_type":"CLASS","centre_examen":"","cap":"","academie":"ACADEMIE D'ENSEIGNEMENT DE MENAKA","examen":"DEF 2024","mention":""},"341":{"prenom":"","nom":"LEYLATA WALET SI DI ALAMI NE31/ 12/ 2009","sexe":"","statut":"REG","ecole":"","option_type":"CLASS","centre_examen":"","cap":"","academie":"ACADEMIE D'ENSEIGNEMENT DE MENAKA","examen":"DEF 2024","mention":""},"342":{"prenom":"","nom":"HAMADAHMED AG SI DI HAM 31/ 12/ 2010","sexe":"","statut":"REG","ecole":"","option_type":"CLASS","centre_examen":"","cap":"","academie":"ACADEMIE D'ENSEIGNEMENT DE MENAKA","examen":"DEF 2024","mention":""},"343":{"prenom":"","nom":"ELHAJI AG SOULEYMANE 31/ 12/ 2009","sexe":"","statut":"REG","ecole":"","option_type":"CLASS","centre_examen":"","cap":"","academie":"ACADEMIE D'ENSEIGNEMENT DE MENAKA","examen":"DEF 2024","mention":""},"346":{"prenom":"","nom":"FATOUMA SYLLA 06/ 06/ 2006","sexe":"","statut":"REG","ecole":"","option_type":"CLASS","centre_examen":"","cap":"","academie":"ACADEMIE D'ENSEIGNEMENT DE MENAKA","examen":"DEF 2024","mention":""},"347":{"prenom":"","nom":"DAOULATA TAMO 31/ 12/ 2006","sexe":"","statut":"REG","ecole":"","option_type":"CLASS","centre_examen":"","cap":"","academie":"ACADEMIE D'ENSEIGNEMENT DE MENAKA","examen":"DEF 2024","mention":""},"348":{"prenom":"","nom":"HAMADA- AHMED AGTERCHE 17/ 01/ 2007","sexe":"","statut":"REG","ecole":"","option_type":"CLASS","centre_examen":"","cap":"","academie":"ACADEMIE D'ENSEIGNEMENT DE MENAKA","examen":"DEF 2024","mention":""},"349":{"prenom":"","nom":"AGALY AG TI LI CHE 31/ 12/ 2011","sexe":"","statut":"REG","ecole":"","option_type":"CLASS","centre_examen":"","cap":"","academie":"ACADEMIE D'ENSEIGNEMENT DE MENAKA","examen":"DEF 2024","mention":""},"350":{"prenom":"","nom":"AI GAI CHATOU TOURE 04/ 01/ 2008","sexe":"","statut":"REG","ecole":"","option_type":"CLASS","centre_examen":"","cap":"","academie":"ACADEMIE D'ENSEIGNEMENT DE MENAKA","examen":"DEF 2024","mention":""},"351":{"prenom":"","nom":"AMADOU TOURE 25/ 10/ 2004","sexe":"","statut":"REG","ecole":"","option_type":"CLASS","centre_examen":"","cap":"","academie":"ACADEMIE D'ENSEIGNEMENT DE MENAKA","examen":"DEF 2024","mention":""},"353":{"prenom":"","nom":"FATOUMATA TOURE 01/ 10/ 2008","sexe":"","statut":"REG","ecole":"","option_type":"CLASS","centre_examen":"","cap":"","academie":"ACADEMIE D'ENSEIGNEMENT DE MENAKA","examen":"DEF 2024","mention":""},"355":{"prenom":"","nom":"MOUNEI SSA ALI OU TOURE 02/ 07/ 2010","sexe":"","statut":"REG","ecole":"","option_type":"CLASS","centre_examen":"","cap":"","academie":"ACADEMIE D'ENSEIGNEMENT DE MENAKA","examen":"DEF 2024","mention":""},"357":{"prenom":"I","nom":"SSOUF TRAORE 06/ 12/ 2006","sexe":"","statut":"REG","ecole":"","option_type":"CLASS","centre_examen":"","cap":"","academie":"ACADEMIE D'ENSEIGNEMENT DE MENAKA","examen":"DEF 2024","mention":""},"358":{"prenom":"","nom":"AMI NATOU I SSI FI WATARA 20/ 06/ 2006","sexe":"","statut":"REG","ecole":"","option_type":"CLASS","centre_examen":"","cap":"","academie":"ACADEMIE D'ENSEIGNEMENT DE MENAKA","examen":"DEF 2024","mention":""},"360":{"prenom":"","nom":"MOHAMED YEHI A 31/ 12/ 2006","sexe":"","statut":"REG","ecole":"","option_type":"CLASS","centre_examen":"","cap":"","academie":"ACADEMIE D'ENSEIGNEMENT DE MENAKA","examen":"DEF 2024","mention":""},"362":{"prenom":"","nom":"HALI DOU YOUNOUSSA 08/ 08/ 2007","sexe":"","statut":"REG","ecole":"","option_type":"CLASS","centre_examen":"","cap":"","academie":"ACADEMIE D'ENSEIGNEMENT DE MENAKA","examen":"DEF 2024","mention":""}}