{"1586":{"prenom":"Amidou","nom":"BENGALY","sexe":"M","statut":"REG","ecole":"","option_type":"CLASS","centre_examen":"","cap":"2°CKLELA","academie":"ACADEMIE D'ENSEIGNEMENT DE SIKASSO","examen":"DEF 2026","mention":""},"3030":{"prenom":"Soumaïla","nom":"BERTHE","sexe":"M","statut":"REG","ecole":"","option_type":"CLASS","centre_examen":"","cap":"2°CKLELA","academie":"ACADEMIE D'ENSEIGNEMENT DE SIKASSO","examen":"DEF 2026","mention":""},"7588":{"prenom":"Yaya","nom":"DIABATE","sexe":"M","statut":"REG","ecole":"","option_type":"CLASS","centre_examen":"","cap":"2°CKLELA","academie":"ACADEMIE D'ENSEIGNEMENT DE SIKASSO","examen":"DEF 2026","mention":""},"7593":{"prenom":"Younoussou","nom":"DIABATE","sexe":"M","statut":"REG","ecole":"","option_type":"CLASS","centre_examen":"","cap":"2°CKLELA","academie":"ACADEMIE D'ENSEIGNEMENT DE SIKASSO","examen":"DEF 2026","mention":""},"11559":{"prenom":"Abdou Karim","nom":"DOMOGO","sexe":"M","statut":"CL","ecole":"","option_type":"CLASS","centre_examen":"","cap":"2°CKLELA","academie":"ACADEMIE D'ENSEIGNEMENT DE SIKASSO","examen":"DEF 2026","mention":""},"11561":{"prenom":"Arouna","nom":"DOMOGO","sexe":"M","statut":"REG","ecole":"","option_type":"CLASS","centre_examen":"","cap":"2°CKLELA","academie":"ACADEMIE D'ENSEIGNEMENT DE SIKASSO","examen":"DEF 2026","mention":""},"11564":{"prenom":"Dramane","nom":"DOMOGO","sexe":"M","statut":"REG","ecole":"","option_type":"CLASS","centre_examen":"","cap":"2°CKLELA","academie":"ACADEMIE D'ENSEIGNEMENT DE SIKASSO","examen":"DEF 2026","mention":""},"12128":{"prenom":"Soumaïla","nom":"GOÏTA","sexe":"M","statut":"REG","ecole":"","option_type":"CLASS","centre_examen":"","cap":"2°CKLELA","academie":"ACADEMIE D'ENSEIGNEMENT DE SIKASSO","examen":"DEF 2026","mention":""},"17192":{"prenom":"Diakalia","nom":"OUONOGO","sexe":"M","statut":"REG","ecole":"","option_type":"CLASS","centre_examen":"","cap":"2°CKLELA","academie":"ACADEMIE D'ENSEIGNEMENT DE SIKASSO","examen":"DEF 2026","mention":""},"17205":{"prenom":"Nouhoum","nom":"OUONOGO","sexe":"M","statut":"REG","ecole":"","option_type":"CLASS","centre_examen":"","cap":"2°CKLELA","academie":"ACADEMIE D'ENSEIGNEMENT DE SIKASSO","examen":"DEF 2026","mention":""},"17211":{"prenom":"Yaya","nom":"OUONOGO","sexe":"M","statut":"REG","ecole":"","option_type":"CLASS","centre_examen":"","cap":"2°CKLELA","academie":"ACADEMIE D'ENSEIGNEMENT DE SIKASSO","examen":"DEF 2026","mention":""},"21682":{"prenom":"Oudou","nom":"SOGODOGO","sexe":"M","statut":"CL","ecole":"","option_type":"CLASS","centre_examen":"","cap":"2°CKLELA","academie":"ACADEMIE D'ENSEIGNEMENT DE SIKASSO","examen":"DEF 2026","mention":""},"22929":{"prenom":"Abdoul Aziz","nom":"TRAORE","sexe":"M","statut":"REG","ecole":"","option_type":"CLASS","centre_examen":"","cap":"2°CKLELA","academie":"ACADEMIE D'ENSEIGNEMENT DE SIKASSO","examen":"DEF 2026","mention":""},"22939":{"prenom":"Abdoul Karim","nom":"TRAORE","sexe":"M","statut":"REG","ecole":"","option_type":"CLASS","centre_examen":"","cap":"2°CKLELA","academie":"ACADEMIE D'ENSEIGNEMENT DE SIKASSO","examen":"DEF 2026","mention":""},"22975":{"prenom":"Abdoulaye","nom":"TRAORE","sexe":"M","statut":"REG","ecole":"","option_type":"CLASS","centre_examen":"","cap":"2°CKLELA","academie":"ACADEMIE D'ENSEIGNEMENT DE SIKASSO","examen":"DEF 2026","mention":""},"25753":{"prenom":"Souleymane","nom":"TRAORE","sexe":"M","statut":"CL","ecole":"","option_type":"CLASS","centre_examen":"","cap":"2°CKLELA","academie":"ACADEMIE D'ENSEIGNEMENT DE SIKASSO","examen":"DEF 2026","mention":""}}