{"19":{"prenom":"Hadijatou Mint","nom":"ABDALLAH","sexe":"","statut":"REG","ecole":"","option_type":"CLASS","centre_examen":"","cap":"BOUREM","academie":"ACADEMIE D'ENSEIGNEMENT DE GAO","examen":"DEF 2024","mention":""},"69":{"prenom":"Abdoul Momine","nom":"ABDOUL AZIZ","sexe":"","statut":"REG","ecole":"","option_type":"CLASS","centre_examen":"BOUREM I","cap":"BOUREM","academie":"ACADEMIE D'ENSEIGNEMENT DE GAO","examen":"DEF 2024","mention":""},"110":{"prenom":"Habibatou","nom":"ABDOUL WAHID","sexe":"","statut":"REG","ecole":"","option_type":"CLASS","centre_examen":"","cap":"BOUREM","academie":"ACADEMIE D'ENSEIGNEMENT DE GAO","examen":"DEF 2024","mention":""},"464":{"prenom":"Oumar","nom":"ABOUBACARINE","sexe":"","statut":"REG","ecole":"","option_type":"CLASS","centre_examen":"BOUREM I","cap":"BOUREM","academie":"ACADEMIE D'ENSEIGNEMENT DE GAO","examen":"DEF 2024","mention":""},"695":{"prenom":"Fatoumata","nom":"ALASSANE","sexe":"","statut":"REG","ecole":"","option_type":"CLASS","centre_examen":"BOUREM I","cap":"BOUREM","academie":"ACADEMIE D'ENSEIGNEMENT DE GAO","examen":"DEF 2024","mention":""},"697":{"prenom":"Ousmana","nom":"ALASSANE","sexe":"","statut":"REG","ecole":"","option_type":"CLASS","centre_examen":"","cap":"BOUREM","academie":"ACADEMIE D'ENSEIGNEMENT DE GAO","examen":"DEF 2024","mention":""},"698":{"prenom":"Assagaïdou","nom":"ALASSANE","sexe":"","statut":"REG","ecole":"","option_type":"CLASS","centre_examen":"","cap":"BOUREM","academie":"ACADEMIE D'ENSEIGNEMENT DE GAO","examen":"DEF 2024","mention":""},"1035":{"prenom":"Hadijatou","nom":"ALPHA","sexe":"","statut":"REG","ecole":"","option_type":"CLASS","centre_examen":"BOUREM I","cap":"BOUREM","academie":"ACADEMIE D'ENSEIGNEMENT DE GAO","examen":"DEF 2024","mention":""},"1036":{"prenom":"Mouneissa","nom":"ALPHA","sexe":"","statut":"REG","ecole":"","option_type":"CLASS","centre_examen":"","cap":"BOUREM","academie":"ACADEMIE D'ENSEIGNEMENT DE GAO","examen":"DEF 2024","mention":""},"1082":{"prenom":"Bintou","nom":"AROUGAYA","sexe":"","statut":"REG","ecole":"","option_type":"CLASS","centre_examen":"","cap":"BOUREM","academie":"ACADEMIE D'ENSEIGNEMENT DE GAO","examen":"DEF 2024","mention":""},"1312":{"prenom":"Aminatou","nom":"CHEHI","sexe":"","statut":"REG","ecole":"","option_type":"CLASS","centre_examen":"","cap":"BOUREM","academie":"ACADEMIE D'ENSEIGNEMENT DE GAO","examen":"DEF 2024","mention":""},"1354":{"prenom":"Hafizou Iboune","nom":"CISSE","sexe":"","statut":"REG","ecole":"","option_type":"CLASS","centre_examen":"GANGANO S/C","cap":"BOUREM","academie":"ACADEMIE D'ENSEIGNEMENT DE GAO","examen":"DEF 2024","mention":""},"1355":{"prenom":"Ibrahim Ahmed","nom":"CISSE","sexe":"","statut":"REG","ecole":"","option_type":"CLASS","centre_examen":"BOUREM I","cap":"BOUREM","academie":"ACADEMIE D'ENSEIGNEMENT DE GAO","examen":"DEF 2024","mention":""},"1590":{"prenom":"Moussa Sadidine","nom":"DIALLO","sexe":"","statut":"REG","ecole":"","option_type":"CLASS","centre_examen":"BOUREM I","cap":"BOUREM","academie":"ACADEMIE D'ENSEIGNEMENT DE GAO","examen":"DEF 2024","mention":""},"1887":{"prenom":"Ibrahim Almahadi","nom":"HAÏDARA","sexe":"","statut":"REG","ecole":"","option_type":"CLASS","centre_examen":"GANGANO S/C","cap":"BOUREM","academie":"ACADEMIE D'ENSEIGNEMENT DE GAO","examen":"DEF 2024","mention":""},"1888":{"prenom":"Hinna","nom":"HAÏDARA","sexe":"","statut":"REG","ecole":"","option_type":"CLASS","centre_examen":"BOUREM I","cap":"BOUREM","academie":"ACADEMIE D'ENSEIGNEMENT DE GAO","examen":"DEF 2024","mention":""},"1890":{"prenom":"Soumeyata Almoustapha","nom":"HAÏDARA","sexe":"","statut":"REG","ecole":"","option_type":"CLASS","centre_examen":"BOUREM I","cap":"BOUREM","academie":"ACADEMIE D'ENSEIGNEMENT DE GAO","examen":"DEF 2024","mention":""},"1903":{"prenom":"Oumar","nom":"HALIDOU","sexe":"","statut":"REG","ecole":"","option_type":"CLASS","centre_examen":"BOUREM I","cap":"BOUREM","academie":"ACADEMIE D'ENSEIGNEMENT DE GAO","examen":"DEF 2024","mention":""},"1953":{"prenom":"Alhassane Ould","nom":"HAMDY","sexe":"","statut":"REG","ecole":"","option_type":"CLASS","centre_examen":"BOUREM I","cap":"BOUREM","academie":"ACADEMIE D'ENSEIGNEMENT DE GAO","examen":"DEF 2024","mention":""},"1979":{"prenom":"Haoua","nom":"HAMMA","sexe":"","statut":"REG","ecole":"","option_type":"CLASS","centre_examen":"","cap":"BOUREM","academie":"ACADEMIE D'ENSEIGNEMENT DE GAO","examen":"DEF 2024","mention":""},"2397":{"prenom":"Mahamadou","nom":"ISSOUFOU","sexe":"","statut":"REG","ecole":"","option_type":"CLASS","centre_examen":"","cap":"BOUREM","academie":"ACADEMIE D'ENSEIGNEMENT DE GAO","examen":"DEF 2024","mention":""},"3897":{"prenom":"Safwana","nom":"MALIKY","sexe":"","statut":"REG","ecole":"","option_type":"CLASS","centre_examen":"GANGANO S/C","cap":"BOUREM","academie":"ACADEMIE D'ENSEIGNEMENT DE GAO","examen":"DEF 2024","mention":""},"4422":{"prenom":"Diabir","nom":"OUSMANA","sexe":"","statut":"REG","ecole":"","option_type":"CLASS","centre_examen":"BOUREM I","cap":"BOUREM","academie":"ACADEMIE D'ENSEIGNEMENT DE GAO","examen":"DEF 2024","mention":""},"4670":{"prenom":"Abdourhamane","nom":"SOULEYMANE","sexe":"","statut":"REG","ecole":"","option_type":"CLASS","centre_examen":"BOUREM I","cap":"BOUREM","academie":"ACADEMIE D'ENSEIGNEMENT DE GAO","examen":"DEF 2024","mention":""},"4770":{"prenom":"Salka Mint","nom":"TAGANA","sexe":"","statut":"REG","ecole":"","option_type":"CLASS","centre_examen":"BOUREM I","cap":"BOUREM","academie":"ACADEMIE D'ENSEIGNEMENT DE GAO","examen":"DEF 2024","mention":""}}